nalangTestKL/test1.py
nalangTestKL/test2.py
nalangTestKL-0.0.0.2.dist-info/METADATA
nalangTestKL-0.0.0.2.dist-info/WHEEL
nalangTestKL-0.0.0.2.dist-info/top_level.txt
nalangTestKL-0.0.0.2.dist-info/RECORD
