Metadata-Version: 2.1
Name: nalangTestKL
Version: 0.0.0.2
Summary: My First Test Package
Home-page: UNKNOWN
Author: Karl Lee
Author-email: chiwon2005@gmail.com
License: MIT
Platform: UNKNOWN
Requires-Python: >=3
